pyController/__init__.py
pyController/__main__.py
pyController/cli.py
pyController/controller.py
pyController-1.0.dist-info/LICENSE
pyController-1.0.dist-info/METADATA
pyController-1.0.dist-info/WHEEL
pyController-1.0.dist-info/entry_points.txt
pyController-1.0.dist-info/top_level.txt
pyController-1.0.dist-info/RECORD
