Metadata-Version: 2.1
Name: pyController
Version: 1.0
Summary: Event Callback system for Bluetooth Controller
Home-page: https://github.com/jbiams77/pyController
Author: Brandon Iams
Author-email: jbiams77@uw.edu
License: UNKNOWN
Keywords: playstation,ps4,controller,robot controls
Platform: UNKNOWN
Classifier: Intended Audience :: Developers
Classifier: Programming Language :: Python :: 2.7
Classifier: Programming Language :: Python :: 3.4
Classifier: Programming Language :: Python :: 3.5
Classifier: Programming Language :: Python :: 3.6
Classifier: Programming Language :: Python :: 3.7
Classifier: Programming Language :: Python :: 3.8
Classifier: License :: OSI Approved :: MIT License
Classifier: Operating System :: POSIX :: Linux
Classifier: Topic :: Software Development :: Libraries
Classifier: Topic :: Software Development :: Libraries :: Python Modules
Classifier: Topic :: Utilities
